virus/__init__.py
virus/core.py
pyvirus-1.0.0.dist-info/LICENSE
pyvirus-1.0.0.dist-info/METADATA
pyvirus-1.0.0.dist-info/WHEEL
pyvirus-1.0.0.dist-info/top_level.txt
pyvirus-1.0.0.dist-info/RECORD
