Metadata-Version: 2.1
Name: pyvirus
Version: 1.0.0
Summary: A Python library for develop virus.
Home-page: https://GitHub.com/mr-r0ot/PyVirus
Author: Mohammad Taha Gorji
Author-email: MohammadTahaGorjiProfile@gmail.com
Classifier: Programming Language :: Python :: 3
Classifier: License :: OSI Approved :: MIT License
Classifier: Operating System :: OS Independent
Requires-Python: >=3.6
License-File: LICENSE
Requires-Dist: pyVmomi
Requires-Dist: pyautogui
Requires-Dist: psutil
